{
  "source": "standartnews",
  "title": "Вълшебен трик премахва ръжда",
  "url": "https://www.standartnews.com/lifestyle-lyubopitno/valsheben-trik-premahva-razhda-633305.html",
  "published_at": "2026-05-11T18:13:40+00:00",
  "summary": "Петната от ръжда по дрехите изглеждат като доживотна присъда за плата, но в действителност могат да бъдат премахнати бързо и евтино. Ключът към успеха е светкавичната реакция и използването на правилните киселини, които разграждат железния оксид. Избягвайте използването на белина, тъй като тя ще фиксира петното завинаги.Метод 1: Силата на лимона и слънцето (за бели и светли дрехи)Това е най-изпитаният и екологичен начин за третиране на памучни и ленени тъкани:Изстискване: Изстискайте пресен лимонов сок директно върху петното от ръжда, докато се напои добре.Осоляване: Поръсете обилно с готварска сол върху мокрото петно. Солният слой ще абсорбира разградената ръжда.Слънчева баня: Изнесете дрехата на директна слънчева светлина за около 30 до 60 минути. Ултравиолетовите лъчи засилват химическата реакция на лимонената киселина.Изпиране: Изплакнете със студена вода и изперете дрехата в пералнята на обичаен режим.Метод 2: Тандемът на белия оцет и содата (за упорити петна)Ако петното е старо и...",
  "full_text": "Петната от ръжда по дрехите изглеждат като доживотна присъда за плата, но в действителност могат да бъдат премахнати бързо и евтино. Ключът към успеха е светкавичната реакция и използването на правилните киселини, които разграждат железния оксид. Избягвайте използването на белина, тъй като тя ще фиксира петното завинаги.\nМетод 1: Силата на лимона и слънцето (за бели и светли дрехи)\nТова е най-изпитаният и екологичен начин за третиране на памучни и ленени тъкани:\nИзстискване: Изстискайте пресен лимонов сок директно върху петното от ръжда, докато се напои добре.\nОсоляване: Поръсете обилно с готварска сол върху мокрото петно. Солният слой ще абсорбира разградената ръжда.\nСлънчева баня: Изнесете дрехата на директна слънчева светлина за около 30 до 60 минути. Ултравиолетовите лъчи засилват химическата реакция на лимонената киселина.\nИзпиране: Изплакнете със студена вода и изперете дрехата в пералнята на обичаен режим.\nМетод 2: Тандемът на белия оцет и содата (за упорити петна)\nАко петното е старо и засъхнало, е необходима по-агресивна домашна паста:\nПриготвяне: Смесете една супена лъжица сода бикарбонат с малко бял дестилиран оцет, докато се получи гъста каша.\nНанасяне: Втрийте пастата върху петното с помощта на стара четка за зъби с мек косъм.\nВреме за действие: Оставете сместа да престои върху плата за около 30 минути, без да оставяте пастата да изсъхне напълно.\nПочистване: Изплакнете обилно с хладка вода и проверете резултата. Ако петното е избледняло, пуснете в пералнята.\nЗлатни правила за безопасност на тъканите\nПреди да започнете процедурата, винаги тествайте лимоновия сок или оцета върху скрит вътрешен шев на дрехата. Това ще ви гарантира, че киселината няма да повреди багрилата на плата. При деликатни материи като коприна и вълна избягвайте търкането и содата – при тях използвайте само разреден лимонов сок и потърсете професионална помощ, ако петното не изчезне веднага.\nПоследвайте ни в Google News Showcase за важните новини\nВижте всички актуални новини от Standartnews.com",
  "fetched_at": "2026-05-11T19:55:06.537983+00:00"
}