{
  "source": "fakti",
  "title": "Разследват убийство в софийско село, мъж и жена са задържани",
  "url": "https://fakti.bg/krimi/1057068-razsledvat-ubiistvo-v-sofiisko-selo-maj-i-jena-sa-zadarjani",
  "published_at": "2026-05-27T09:22:25+00:00",
  "summary": "<img src=\"https://cdn4.focus.bg/fakti/photos/big/37e/razsledvat-ubiistvo-v-sofiisko-selo-maj-i-jena-sa-zadarjani-1.webp\" /><p>Полицията разследва инцидент, станал във вчерашния ден, 26 май в софийското село Ямна, съобщават от ОДМВР-София.</p>\n\n<p>Сигнал за починалия в частен дом мъж е бил подаден около 6 часа сутринта. При огледа на местопроизшествието по тялото са били установени видими следи от насилие. За срок до 24 часа са задържани обитателят на адреса и млада жена.</p>\n\n<p>Образувано е досъдебно производство за умишлено убийство. Действията по разследването продължават под ръководството на прокуратурата.</p>",
  "full_text": "Полицията разследва инцидент, станал във вчерашния ден, 26 май в софийското село Ямна, съобщават от ОДМВР-София.\nСигнал за починалия в частен дом мъж е бил подаден около 6 часа сутринта. При огледа на местопроизшествието по тялото са били установени видими следи от насилие. За срок до 24 часа са задържани обитателят на адреса и млада жена.\nОбразувано е досъдебно производство за умишлено убийство. Действията по разследването продължават под ръководството на прокуратурата.\nПоставете оценка:\nОценка 1 от 2 гласа.\nНапиши коментар:\nКОМЕНТАРИ КЪМ СТАТИЯТА\n1 Опааа\n12:25 27.05.2026\n2 Първоначално си помислих\n12:48 27.05.2026",
  "fetched_at": "2026-05-27T09:56:22.895555+00:00"
}