{
  "source": "banker",
  "title": "Министър Иван Шишков разпореди проверка на мантинелите на магистралите",
  "url": "https://banker.bg/2026/06/26/ministar-ivan-shishkov-razporedi-proverka-na-mantinelite-na-magistralite/",
  "published_at": "2026-06-26T15:05:52+00:00",
  "summary": "<img alt=\"Министър Иван Шишков разпореди проверка на мантинелите на магистралите\" class=\"webfeedsFeaturedVisual wp-post-image\" height=\"150\" src=\"https://banker.bg/wp-content/uploads/c1d950c2-d14b-4647-b875-8998198a5748-150x150.webp\" style=\"float: left; margin-right: 5px;\" title=\"Министър Иван Шишков разпореди проверка на мантинелите на магистралите 26\" width=\"150\" /><img alt=\"Министър Иван Шишков разпореди проверка на мантинелите на магистралите\" class=\"attachment-thumbnail size-thumbnail wp-post-image\" height=\"150\" src=\"https://banker.bg/wp-content/uploads/c1d950c2-d14b-4647-b875-8998198a5748-150x150.webp\" title=\"Министър Иван Шишков разпореди проверка на мантинелите на магистралите 25\" width=\"150\" />Министърът на регионалното развитие и благоустройството Иван Шишков съобщи, че е разпоредил и от днес тече проверка дали качествата на материалите, от които са произведени мантинелите на автомагистралите &#8222;Тракия&#8220; и &#8222;Струма&#8220; в участъците на двата инцидента от тази седмица, при които тирове преминаха през тях, отговарят на изискванията: &#8222;Тази мантинела, където е станал трагичният случай, [&#8230;]",
  "full_text": "Министърът на регионалното развитие и благоустройството Иван Шишков съобщи, че е разпоредил и от днес тече проверка дали качествата на материалите, от които са произведени мантинелите на автомагистралите „Тракия“ и „Струма“ в участъците на двата инцидента от тази седмица, при които тирове преминаха през тях, отговарят на изискванията:\n„Тази мантинела, където е станал трагичният случай, не е подменена. Изискването по закон, когато е приета наредбата 2024 г., е в рамките на 10 години да бъдат подменени. Странният случай обаче е, че в другата катастрофа, която, за щастие, е без човешки жертви, мантинелата е подменена. Затова в момента съм се разпоредил да се направи проверка и на тези мантинели, които са подменени, дали отговарят на изискванията – такива, каквито следва да бъдат“, каза той.\nРегионалният министър обяви, че магистралите в България са проектирани при параметри за поставяне на мантинели и на тях не могат да се поставят бетонни пътни прегради. При проектирането на нови магистрали ще се анализира дали ще е по-добре да се поставят бетонни прегради, но Шишков предупреди:\n„Пазят много по-добре от катастрофи, но когато се касае за тирове, какъвто е случаят. Лошото, обаче е, че когато става въпрос пък за автомобили, тъй като автомобилите, блъскайки се в тази твърда повърхнина, каквато е бетонът, разбира се, ще има обратен ефект за водача на автомобила. Не можем да кажем, че има еднозначен отговор“.",
  "fetched_at": "2026-06-26T17:52:48.773672+00:00"
}