{
  "source": "fakti",
  "title": "Промяна в правилата на \"Оскарите\": Без повече филми с AI и повече номинации за актьори",
  "url": "https://fakti.bg/life/1051914-promana-v-pravilata-na-oskarite-bez-poveche-filmi-s-ai-i-poveche-nominacii-za-aktyori",
  "published_at": "2026-05-02T11:28:14+00:00",
  "summary": "<img src=\"https://cdn4.focus.bg/fakti/photos/big/d95/promana-v-pravilata-na-oskarite-bez-poveche-filmi-s-ai-i-poveche-nominacii-za-aktyori-1.webp\" /><p><strong>Академията за кинематографично изкуство и наука одобри съществен пакет от нови и актуализирани правила за 99-ото издание на наградите Оскар, планирано за 2027 г., като промените отразяват еволюцията в стандартите за допустимост, авторство и международно участие.</strong></p>\n\n<p>Най-съществената промяна засяга актьорските категории. <strong>За първи път изпълнители ще могат да получат повече от една номинация в рамките на една и съща категория, ако техните изпълнения попаднат сред първите пет по гласове</strong>. Така се премахва досегашното ограничение, при което само най-високо класираното изпълнение оставаше в надпреварата. Новият модел цели да ограничи т.нар. &bdquo;категорийни манипулации&ldquo;, при които кампаниите насочват актьорски участия към поддържащи роли, за да избегнат вътрешна конкуренция.</p>\n\n<p>Исторически подобни случаи не са рядкост. <strong>През 2008 г. Кейт Уинслет води паралелна кампания за ролите си в Revolutionary Road и The Reader, като впоследствие печели &bdquo;Оскар&ldquo; за най-добра актриса. </strong>Според новите правила подобни двойни номинации вече биха били възможни в рамките на една категория.</p>\n\n<p>Академията въведе и уточнения относно допустимостта на актьорските изпълнения, като подчерта, че <strong>ще се разглеждат само роли, изпълнени от реални актьори със съгласие и ясно кредитиране. Това идва на фона на нарастващите дебати около използването на дигитални двойници и технологии, свързани с изкуствен интелект. </strong>В категориите за сценарий вече изрично се изисква текстовете да бъдат създадени от хора, като Академията си запазва правото да изисква допълнителна информация за степента на човешко участие при използване на генеративни технологии.</p>\n\n<p><strong>Съществена реформа беше въведена и в категорията за международен филм.</strong> Вече е възможно повече от една продукция от една и съща държава да достигне до номинации, ако отговаря на определени критерии. Освен чрез национални селекционни комисии, филми на чужд език могат да се класират и чрез спечелване на водещи награди на фестивали като Филмов фестивал в Кан (Златна палма), Берлински международен филмов фестивал (Златна мечка) и Венециански филмов фестивал (Златен лъв). Промяната е вдъхновена от случаи като &quot;Анатомия на падането&quot;, който не беше избран от Франция, но впоследствие получи множество номинации и награда за оригинален сценарий.</p>\n\n<p>Други промени включват<strong> увеличаване на броя на отличията в категорията за кастинг до три, въвеждане на фиксиран кратък списък от 20 филма в категорията операторско майсторство, както и по-строги изисквания за участие в гласуването в категории като визуални ефекти и грим.</strong> В категорията за оригинална песен се изисква представянето на конкретен видео откъс, включващ последните секунди преди финалните надписи.</p>\n\n<p>Академията актуализира и правилата за промоционални кампании, като допуска по-широко участие в дискусии и въвежда задължителни изисквания за достъпност при комуникация със своите членове.</p>\n\n<p><strong>Ключовите срокове за кандидатстване за 99-ите &bdquo;Оскари&ldquo; започват през август 2026 г., като допустими са филми с премиера между 1 януари и 31 декември същата година. </strong>Очакванията към селекцията вече са високи, с оглед на предстоящи заглавия като Dune: Part Three на Дени Вилньов и нов проект на Алехандро Гонсалес Иняриту.</p>\n\n<p><strong>99-ата церемония по връчването на наградите &bdquo;Оскар&ldquo; ще се състои на 14 март 2027 г. в театър &bdquo;Долби&ldquo; в Холивуд и ще бъде излъчена на живо в над 200 държави.</strong></p>",
  "full_text": "Академията за кинематографично изкуство и наука одобри съществен пакет от нови и актуализирани правила за 99-ото издание на наградите Оскар, планирано за 2027 г., като промените отразяват еволюцията в стандартите за допустимост, авторство и международно участие.\nНай-съществената промяна засяга актьорските категории. За първи път изпълнители ще могат да получат повече от една номинация в рамките на една и съща категория, ако техните изпълнения попаднат сред първите пет по гласове. Така се премахва досегашното ограничение, при което само най-високо класираното изпълнение оставаше в надпреварата. Новият модел цели да ограничи т.нар. „категорийни манипулации“, при които кампаниите насочват актьорски участия към поддържащи роли, за да избегнат вътрешна конкуренция.\nИсторически подобни случаи не са рядкост. През 2008 г. Кейт Уинслет води паралелна кампания за ролите си в Revolutionary Road и The Reader, като впоследствие печели „Оскар“ за най-добра актриса. Според новите правила подобни двойни номинации вече биха били възможни в рамките на една категория.\nАкадемията въведе и уточнения относно допустимостта на актьорските изпълнения, като подчерта, че ще се разглеждат само роли, изпълнени от реални актьори със съгласие и ясно кредитиране. Това идва на фона на нарастващите дебати около използването на дигитални двойници и технологии, свързани с изкуствен интелект. В категориите за сценарий вече изрично се изисква текстовете да бъдат създадени от хора, като Академията си запазва правото да изисква допълнителна информация за степента на човешко участие при използване на генеративни технологии.\nСъществена реформа беше въведена и в категорията за международен филм. Вече е възможно повече от една продукция от една и съща държава да достигне до номинации, ако отговаря на определени критерии. Освен чрез национални селекционни комисии, филми на чужд език могат да се класират и чрез спечелване на водещи награди на фестивали като Филмов фестивал в Кан (Златна палма), Берлински международен филмов фестивал (Златна мечка) и Венециански филмов фестивал (Златен лъв). Промяната е вдъхновена от случаи като \"Анатомия на падането\", който не беше избран от Франция, но впоследствие получи множество номинации и награда за оригинален сценарий.\nДруги промени включват увеличаване на броя на отличията в категорията за кастинг до три, въвеждане на фиксиран кратък списък от 20 филма в категорията операторско майсторство, както и по-строги изисквания за участие в гласуването в категории като визуални ефекти и грим. В категорията за оригинална песен се изисква представянето на конкретен видео откъс, включващ последните секунди преди финалните надписи.\nАкадемията актуализира и правилата за промоционални кампании, като допуска по-широко участие в дискусии и въвежда задължителни изисквания за достъпност при комуникация със своите членове.\nКлючовите срокове за кандидатстване за 99-ите „Оскари“ започват през август 2026 г., като допустими са филми с премиера между 1 януари и 31 декември същата година. Очакванията към селекцията вече са високи, с оглед на предстоящи заглавия като Dune: Part Three на Дени Вилньов и нов проект на Алехандро Гонсалес Иняриту.\n99-ата церемония по връчването на наградите „Оскар“ ще се състои на 14 март 2027 г. в театър „Долби“ в Холивуд и ще бъде излъчена на живо в над 200 държави.\nНапиши коментар:\nКОМЕНТАРИ КЪМ СТАТИЯТА\n1 Мара Бакалова\n14:34 02.05.2026\n2 Този коментар е премахнат от модератор.",
  "fetched_at": "2026-05-02T13:17:31.711668+00:00"
}