{
  "source": "actualno",
  "title": "Стрелял с прашка по деца: Задържаха раздразнен от шума мъж",
  "url": "https://www.actualno.com/crime/streljal-s-prashka-po-deca-zadyrjaha-razdraznen-ot-shuma-myj-news_2595449.html",
  "published_at": "2026-05-18T07:04:00+00:00",
  "summary": "Мъж на 63 години от Велико Търново е задържан от служители на полицейското управление, след като е стрелял с прашка по д...",
  "full_text": "Мъж на 63 години от Велико Търново е задържан от служители на полицейското управление, след като е стрелял с прашка по деца. Няколко от децата са с леки наранявания, съобщиха от пресцентъра на Областната дирекция на МВР, цитирани от БТА.\nСигнал за случая е получен в неделя около 19:00 часа. По данни на подателя на сигнала, негов съсед е стрелял по деца, имало и пострадали.\nИзпратеният на адреса в областния град полицейски екип е установил, че 63-годишен местен жител се дразнел от шума на играещи около блока деца и стрелял по тях с прашка с топчета.\nОще: Домашно насилие 2024: Най-много жертви са деца\nУстановено е, че няколко от децата са с леки наранявания. Извършено е претърсване в жилището на мъжа. Прашката и топчетата са иззети. Той е задържан за срок до 24 часа по Закона за МВР. По случая се води досъдебно производство, допълниха от Областната дирекция.\nВ събота полицията задържа мъжа, обвинен за стрелба в столичния квартал “Надежда“.\nОще: Без надзор: Родители прибират децата си с рани и синини от детска градина",
  "fetched_at": "2026-05-18T08:08:02.971952+00:00"
}